<awards><record><id>tt7286456</id><award>Golden Globe</award><count>2</count></record><record><id>tt7286456</id><award>BAFTA Film Award</award><count>3</count></record><record><id>tt7286456</id><award>Oscar</award><count>2</count></record><record><id>tt0110912</id><award>Oscar</award><count>1</count></record><record><id>tt0110912</id><award>Golden Globe</award><count>1</count></record><record><id>tt0110912</id><award>BAFTA Film Award</award><count>2</count></record><record><id>tt3281548</id><award>BAFTA Film Award</award><count>1</count></record><record><id>tt3281548</id><award>Oscar</award><count>1</count></record><record><id>tt0038650</id><award>Golden Globe</award><count>1</count></record><record><id>tt1392190</id><award>BAFTA Film Award</award><count>4</count></record><record><id>tt1392190</id><award>Oscar</award><count>6</count></record><record><id>tt8579674</id><award>Golden Globe</award><count>2</count></record><record><id>tt8579674</id><award>BAFTA Film Award</award><count>7</count></record><record><id>tt8579674</id><award>Oscar</award><count>3</count></record><record><id>tt2584384</id><award>BAFTA Film Award</award><count>1</count></record><record><id>tt2584384</id><award>Oscar</award><count>1</count></record><record><id>tt6751668</id><award>Golden Globe</award><count>1</count></record><record><id>tt6751668</id><award>BAFTA Film Award</award><count>2</count></record><record><id>tt6751668</id><award>Oscar</award><count>4</count></record><record><id>tt0361748</id><award>Oscar</award><count>1</count></record><record><id>tt0361748</id><award>Golden Globe</award><count>1</count></record><record><id>tt0361748</id><award>BAFTA Film Award</award><count>1</count></record><record><id>tt0099685</id><award>Oscar</award><count>1</count></record><record><id>tt0099685</id><award>BAFTA Film Award</award><count>5</count></record><record><id>tt1375666</id><award>BAFTA Film Award</award><count>3</count></record><record><id>tt1375666</id><award>Oscar</award><count>4</count></record><record><id>tt4729430</id><award>BAFTA Film Award</award><count>1</count></record><record><id>tt0120338</id><award>Oscar</award><count>11</count></record><record><id>tt0120338</id><award>Golden Globe</award><count>4</count></record><record><id>tt1517451</id><award>Golden Globe</award><count>1</count></record><record><id>tt1517451</id><award>Oscar</award><count>1</count></record><record><id>tt1517451</id><award>BAFTA Film Award</award><count>1</count></record><record><id>tt1856101</id><award>BAFTA Film Award</award><count>2</count></record><record><id>tt1856101</id><award>Oscar</award><count>2</count></record><record><id>tt0133093</id><award>Oscar</award><count>4</count></record><record><id>tt0133093</id><award>BAFTA Film Award</award><count>2</count></record><record><id>tt7131622</id><award>Golden Globe</award><count>3</count></record><record><id>tt7131622</id><award>BAFTA Film Award</award><count>1</count></record><record><id>tt7131622</id><award>Oscar</award><count>2</count></record><record><id>tt0120737</id><award>Oscar</award><count>4</count></record><record><id>tt0120737</id><award>BAFTA Film Award</award><count>3</count></record><record><id>tt0039628</id><award>Oscar</award><count>3</count></record><record><id>tt0039628</id><award>Golden Globe</award><count>2</count></record><record><id>tt4633694</id><award>Golden Globe</award><count>1</count></record><record><id>tt4633694</id><award>BAFTA Film Award</award><count>1</count></record><record><id>tt4633694</id><award>Oscar</award><count>1</count></record><record><id>tt0068646</id><award>Oscar</award><count>3</count></record><record><id>tt0068646</id><award>Golden Globe</award><count>5</count></record><record><id>tt0033467</id><award>Oscar</award><count>1</count></record><record><id>tt0088763</id><award>Oscar</award><count>1</count></record><record><id>tt0468569</id><award>Oscar</award><count>2</count></record><record><id>tt0468569</id><award>Golden Globe</award><count>1</count></record><record><id>tt0468569</id><award>BAFTA Film Award</award><count>1</count></record><record><id>tt0816692</id><award>Oscar</award><count>1</count></record><record><id>tt0816692</id><award>BAFTA Film Award</award><count>1</count></record><record><id>tt0076759</id><award>Oscar</award><count>6</count></record><record><id>tt0076759</id><award>Golden Globe</award><count>1</count></record><record><id>tt0076759</id><award>BAFTA Film Award</award><count>1</count></record><record><id>tt6966692</id><award>Golden Globe</award><count>3</count></record><record><id>tt6966692</id><award>BAFTA Film Award</award><count>1</count></record><record><id>tt6966692</id><award>Oscar</award><count>3</count></record><record><id>tt5726616</id><award>BAFTA Film Award</award><count>1</count></record><record><id>tt5726616</id><award>Oscar</award><count>1</count></record><record><id>tt0993846</id><award>Golden Globe</award><count>1</count></record><record><id>tt1201607</id><award>BAFTA Film Award</award><count>1</count></record><record><id>tt0172495</id><award>Oscar</award><count>5</count></record><record><id>tt0172495</id><award>Golden Globe</award><count>2</count></record><record><id>tt0172495</id><award>BAFTA Film Award</award><count>4</count></record><record><id>tt0071562</id><award>Oscar</award><count>6</count></record><record><id>tt0071562</id><award>BAFTA Film Award</award><count>1</count></record><record><id>tt0080684</id><award>Oscar</award><count>1</count></record><record><id>tt0102926</id><award>Oscar</award><count>5</count></record><record><id>tt0102926</id><award>Golden Globe</award><count>1</count></record><record><id>tt0102926</id><award>BAFTA Film Award</award><count>2</count></record><record><id>tt1663202</id><award>Golden Globe</award><count>3</count></record><record><id>tt1663202</id><award>BAFTA Film Award</award><count>4</count></record><record><id>tt1663202</id><award>Oscar</award><count>3</count></record><record><id>tt2488496</id><award>BAFTA Film Award</award><count>1</count></record><record><id>tt0407887</id><award>Oscar</award><count>4</count></record><record><id>tt0407887</id><award>Golden Globe</award><count>1</count></record><record><id>tt0108052</id><award>Oscar</award><count>7</count></record><record><id>tt0108052</id><award>Golden Globe</award><count>3</count></record><record><id>tt0108052</id><award>BAFTA Film Award</award><count>6</count></record><record><id>tt0167261</id><award>Oscar</award><count>2</count></record><record><id>tt0167261</id><award>BAFTA Film Award</award><count>2</count></record><record><id>tt0094226</id><award>Oscar</award><count>1</count></record><record><id>tt0094226</id><award>Golden Globe</award><count>1</count></record><record><id>tt0094226</id><award>BAFTA Film Award</award><count>1</count></record><record><id>tt0330373</id><award>BAFTA Film Award</award><count>1</count></record><record><id>tt0059742</id><award>Oscar</award><count>5</count></record><record><id>tt0059742</id><award>Golden Globe</award><count>2</count></record><record><id>tt0119116</id><award>BAFTA Film Award</award><count>1</count></record><record><id>tt0116282</id><award>Oscar</award><count>2</count></record><record><id>tt0099487</id><award>BAFTA Film Award</award><count>1</count></record><record><id>tt0169547</id><award>Oscar</award><count>5</count></record><record><id>tt0169547</id><award>Golden Globe</award><count>3</count></record><record><id>tt0169547</id><award>BAFTA Film Award</award><count>5</count></record><record><id>tt0073486</id><award>Oscar</award><count>5</count></record><record><id>tt0073486</id><award>Golden Globe</award><count>6</count></record><record><id>tt0073486</id><award>BAFTA Film Award</award><count>6</count></record><record><id>tt2582802</id><award>Golden Globe</award><count>1</count></record><record><id>tt2582802</id><award>BAFTA Film Award</award><count>3</count></record><record><id>tt2582802</id><award>Oscar</award><count>3</count></record><record><id>tt0109830</id><award>Oscar</award><count>6</count></record><record><id>tt0109830</id><award>Golden Globe</award><count>3</count></record><record><id>tt0109830</id><award>BAFTA Film Award</award><count>1</count></record><record><id>tt1950186</id><award>BAFTA Film Award</award><count>1</count></record><record><id>tt1950186</id><award>Oscar</award><count>2</count></record><record><id>tt0167260</id><award>Oscar</award><count>11</count></record><record><id>tt0167260</id><award>Golden Globe</award><count>4</count></record><record><id>tt0167260</id><award>BAFTA Film Award</award><count>4</count></record><record><id>tt0381061</id><award>BAFTA Film Award</award><count>1</count></record><record><id>tt0119217</id><award>Oscar</award><count>2</count></record><record><id>tt0119217</id><award>Golden Globe</award><count>1</count></record><record><id>tt0086190</id><award>BAFTA Film Award</award><count>1</count></record><record><id>tt0107290</id><award>Oscar</award><count>3</count></record><record><id>tt0107290</id><award>BAFTA Film Award</award><count>1</count></record><record><id>tt5013056</id><award>Oscar</award><count>3</count></record><record><id>tt5013056</id><award>BAFTA Film Award</award><count>1</count></record><record><id>tt0477348</id><award>Oscar</award><count>4</count></record><record><id>tt0477348</id><award>Golden Globe</award><count>2</count></record><record><id>tt0477348</id><award>BAFTA Film Award</award><count>2</count></record><record><id>tt1853728</id><award>Golden Globe</award><count>2</count></record><record><id>tt1853728</id><award>BAFTA Film Award</award><count>2</count></record><record><id>tt1853728</id><award>Oscar</award><count>2</count></record><record><id>tt1454029</id><award>Golden Globe</award><count>1</count></record><record><id>tt1454029</id><award>BAFTA Film Award</award><count>1</count></record><record><id>tt1454029</id><award>Oscar</award><count>1</count></record><record><id>tt1568346</id><award>Oscar</award><count>1</count></record><record><id>tt0082971</id><award>Oscar</award><count>4</count></record><record><id>tt0082971</id><award>BAFTA Film Award</award><count>1</count></record><record><id>tt5052448</id><award>Oscar</award><count>1</count></record><record><id>tt0469494</id><award>Oscar</award><count>2</count></record><record><id>tt0469494</id><award>Golden Globe</award><count>1</count></record><record><id>tt0469494</id><award>BAFTA Film Award</award><count>1</count></record><record><id>tt1596363</id><award>BAFTA Film Award</award><count>1</count></record><record><id>tt1596363</id><award>Oscar</award><count>1</count></record><record><id>tt3890160</id><award>BAFTA Film Award</award><count>1</count></record><record><id>tt0120815</id><award>Oscar</award><count>5</count></record><record><id>tt0120815</id><award>Golden Globe</award><count>2</count></record><record><id>tt0120815</id><award>BAFTA Film Award</award><count>2</count></record><record><id>tt5027774</id><award>BAFTA Film Award</award><count>5</count></record><record><id>tt5027774</id><award>Golden Globe</award><count>4</count></record><record><id>tt5027774</id><award>Oscar</award><count>2</count></record><record><id>tt0338013</id><award>Oscar</award><count>1</count></record><record><id>tt0338013</id><award>BAFTA Film Award</award><count>2</count></record><record><id>tt3783958</id><award>Golden Globe</award><count>7</count></record><record><id>tt3783958</id><award>BAFTA Film Award</award><count>4</count></record><record><id>tt3783958</id><award>Oscar</award><count>6</count></record><record><id>tt1798709</id><award>Golden Globe</award><count>1</count></record><record><id>tt1798709</id><award>Oscar</award><count>1</count></record><record><id>tt0083658</id><award>BAFTA Film Award</award><count>3</count></record><record><id>tt2119532</id><award>BAFTA Film Award</award><count>1</count></record><record><id>tt2119532</id><award>Oscar</award><count>2</count></record><record><id>tt0499549</id><award>Oscar</award><count>3</count></record><record><id>tt0499549</id><award>Golden Globe</award><count>2</count></record><record><id>tt0499549</id><award>BAFTA Film Award</award><count>2</count></record><record><id>tt3460252</id><award>Golden Globe</award><count>1</count></record><record><id>tt3460252</id><award>BAFTA Film Award</award><count>1</count></record><record><id>tt3460252</id><award>Oscar</award><count>1</count></record><record><id>tt0325980</id><award>BAFTA Film Award</award><count>1</count></record><record><id>tt1285016</id><award>Golden Globe</award><count>4</count></record><record><id>tt1285016</id><award>BAFTA Film Award</award><count>2</count></record><record><id>tt1285016</id><award>Oscar</award><count>3</count></record><record><id>tt0075314</id><award>BAFTA Film Award</award><count>2</count></record><record><id>tt1727824</id><award>Golden Globe</award><count>2</count></record><record><id>tt1727824</id><award>BAFTA Film Award</award><count>2</count></record><record><id>tt1727824</id><award>Oscar</award><count>4</count></record><record><id>tt0104691</id><award>Oscar</award><count>1</count></record><record><id>tt0104691</id><award>BAFTA Film Award</award><count>2</count></record><record><id>tt0078788</id><award>Oscar</award><count>2</count></record><record><id>tt0078788</id><award>Golden Globe</award><count>3</count></record><record><id>tt0078788</id><award>BAFTA Film Award</award><count>2</count></record><record><id>tt0078754</id><award>Oscar</award><count>4</count></record><record><id>tt0078754</id><award>BAFTA Film Award</award><count>2</count></record><record><id>tt2278388</id><award>Golden Globe</award><count>1</count></record><record><id>tt2278388</id><award>BAFTA Film Award</award><count>5</count></record><record><id>tt2278388</id><award>Oscar</award><count>4</count></record><record><id>tt0078748</id><award>Oscar</award><count>1</count></record><record><id>tt0078748</id><award>BAFTA Film Award</award><count>2</count></record><record><id>tt0114814</id><award>Oscar</award><count>2</count></record><record><id>tt0114814</id><award>BAFTA Film Award</award><count>2</count></record><record><id>tt0087332</id><award>BAFTA Film Award</award><count>1</count></record><record><id>tt0090605</id><award>Oscar</award><count>2</count></record><record><id>tt0090605</id><award>BAFTA Film Award</award><count>1</count></record><record><id>tt0268978</id><award>Oscar</award><count>4</count></record><record><id>tt0268978</id><award>Golden Globe</award><count>4</count></record><record><id>tt0268978</id><award>BAFTA Film Award</award><count>2</count></record><record><id>tt2380307</id><award>Golden Globe</award><count>1</count></record><record><id>tt2380307</id><award>BAFTA Film Award</award><count>1</count></record><record><id>tt2380307</id><award>Oscar</award><count>2</count></record><record><id>tt0112573</id><award>Oscar</award><count>5</count></record><record><id>tt0112573</id><award>Golden Globe</award><count>1</count></record><record><id>tt0112573</id><award>BAFTA Film Award</award><count>3</count></record><record><id>tt0118749</id><award>Golden Globe</award><count>1</count></record><record><id>tt0120382</id><award>Golden Globe</award><count>3</count></record><record><id>tt0120382</id><award>BAFTA Film Award</award><count>2</count></record><record><id>tt0050083</id><award>BAFTA Film Award</award><count>1</count></record><record><id>tt0245429</id><award>Oscar</award><count>1</count></record><record><id>tt0264464</id><award>BAFTA Film Award</award><count>1</count></record><record><id>tt2084970</id><award>Oscar</award><count>1</count></record><record><id>tt0032138</id><award>Oscar</award><count>2</count></record><record><id>tt1504320</id><award>Golden Globe</award><count>1</count></record><record><id>tt1504320</id><award>BAFTA Film Award</award><count>5</count></record><record><id>tt1504320</id><award>Oscar</award><count>4</count></record><record><id>tt0118799</id><award>Oscar</award><count>3</count></record><record><id>tt0118799</id><award>BAFTA Film Award</award><count>1</count></record><record><id>tt0118799</id><award>Golden Globe</award><count>4</count></record><record><id>tt3659388</id><award>Golden Globe</award><count>2</count></record><record><id>tt0083866</id><award>Oscar</award><count>4</count></record><record><id>tt0083866</id><award>Golden Globe</award><count>2</count></record><record><id>tt0083866</id><award>BAFTA Film Award</award><count>1</count></record><record><id>tt0470752</id><award>Oscar</award><count>1</count></record><record><id>tt0099348</id><award>Oscar</award><count>7</count></record><record><id>tt0099348</id><award>Golden Globe</award><count>3</count></record><record><id>tt0112384</id><award>Oscar</award><count>2</count></record><record><id>tt0112384</id><award>BAFTA Film Award</award><count>2</count></record><record><id>tt0796366</id><award>Oscar</award><count>1</count></record><record><id>tt7653254</id><award>Golden Globe</award><count>1</count></record><record><id>tt7653254</id><award>BAFTA Film Award</award><count>1</count></record><record><id>tt7653254</id><award>Oscar</award><count>1</count></record><record><id>tt3170832</id><award>Golden Globe</award><count>1</count></record><record><id>tt3170832</id><award>BAFTA Film Award</award><count>1</count></record><record><id>tt3170832</id><award>Oscar</award><count>1</count></record><record><id>tt2543164</id><award>BAFTA Film Award</award><count>1</count></record><record><id>tt2543164</id><award>Oscar</award><count>1</count></record><record><id>tt0110357</id><award>Oscar</award><count>2</count></record><record><id>tt0110357</id><award>Golden Globe</award><count>3</count></record><record><id>tt1979376</id><award>Oscar</award><count>1</count></record><record><id>tt0097576</id><award>Oscar</award><count>1</count></record><record><id>tt0062622</id><award>Oscar</award><count>1</count></record><record><id>tt0062622</id><award>BAFTA Film Award</award><count>3</count></record><record><id>tt0947798</id><award>Golden Globe</award><count>1</count></record><record><id>tt0947798</id><award>BAFTA Film Award</award><count>1</count></record><record><id>tt0947798</id><award>Oscar</award><count>1</count></record><record><id>tt0103064</id><award>Oscar</award><count>4</count></record><record><id>tt0103064</id><award>BAFTA Film Award</award><count>2</count></record><record><id>tt1074638</id><award>Golden Globe</award><count>1</count></record><record><id>tt1074638</id><award>Oscar</award><count>2</count></record><record><id>tt0457430</id><award>Oscar</award><count>3</count></record><record><id>tt0457430</id><award>BAFTA Film Award</award><count>3</count></record><record><id>tt0382932</id><award>Oscar</award><count>1</count></record><record><id>tt0382932</id><award>BAFTA Film Award</award><count>1</count></record><record><id>tt0382932</id><award>Golden Globe</award><count>1</count></record><record><id>tt2948356</id><award>Golden Globe</award><count>1</count></record><record><id>tt2948356</id><award>Oscar</award><count>1</count></record><record><id>tt2024544</id><award>Golden Globe</award><count>1</count></record><record><id>tt2024544</id><award>BAFTA Film Award</award><count>2</count></record><record><id>tt2024544</id><award>Oscar</award><count>3</count></record><record><id>tt1403865</id><award>BAFTA Film Award</award><count>1</count></record><record><id>tt0166924</id><award>BAFTA Film Award</award><count>1</count></record><record><id>tt0206634</id><award>BAFTA Film Award</award><count>2</count></record><record><id>tt0091763</id><award>Oscar</award><count>4</count></record><record><id>tt0091763</id><award>Golden Globe</award><count>3</count></record><record><id>tt0091763</id><award>BAFTA Film Award</award><count>2</count></record><record><id>tt1119646</id><award>Golden Globe</award><count>1</count></record><record><id>tt0097165</id><award>Oscar</award><count>1</count></record><record><id>tt0097165</id><award>BAFTA Film Award</award><count>2</count></record><record><id>tt0077416</id><award>Oscar</award><count>5</count></record><record><id>tt0077416</id><award>Golden Globe</award><count>1</count></record><record><id>tt0077416</id><award>BAFTA Film Award</award><count>2</count></record><record><id>tt0211915</id><award>BAFTA Film Award</award><count>2</count></record><record><id>tt0107048</id><award>BAFTA Film Award</award><count>1</count></record><record><id>tt0105323</id><award>Oscar</award><count>1</count></record><record><id>tt0105323</id><award>Golden Globe</award><count>3</count></record><record><id>tt0181875</id><award>Oscar</award><count>1</count></record><record><id>tt0181875</id><award>Golden Globe</award><count>2</count></record><record><id>tt0181875</id><award>BAFTA Film Award</award><count>2</count></record><record><id>tt0421715</id><award>Oscar</award><count>3</count></record><record><id>tt0421715</id><award>BAFTA Film Award</award><count>3</count></record><record><id>tt0105695</id><award>Oscar</award><count>4</count></record><record><id>tt0105695</id><award>Golden Globe</award><count>2</count></record><record><id>tt0105695</id><award>BAFTA Film Award</award><count>1</count></record><record><id>tt0388795</id><award>Oscar</award><count>3</count></record><record><id>tt0388795</id><award>Golden Globe</award><count>4</count></record><record><id>tt0388795</id><award>BAFTA Film Award</award><count>3</count></record><record><id>tt0253474</id><award>Oscar</award><count>3</count></record><record><id>tt0253474</id><award>BAFTA Film Award</award><count>1</count></record><record><id>tt0253474</id><award>Golden Globe</award><count>1</count></record><record><id>tt0335266</id><award>Oscar</award><count>1</count></record><record><id>tt0335266</id><award>Golden Globe</award><count>3</count></record><record><id>tt0335266</id><award>BAFTA Film Award</award><count>3</count></record><record><id>tt1045658</id><award>Golden Globe</award><count>1</count></record><record><id>tt1045658</id><award>BAFTA Film Award</award><count>1</count></record><record><id>tt1045658</id><award>Oscar</award><count>1</count></record><record><id>tt0126029</id><award>Oscar</award><count>1</count></record><record><id>tt0126029</id><award>BAFTA Film Award</award><count>1</count></record><record><id>tt0100157</id><award>Oscar</award><count>1</count></record><record><id>tt0100157</id><award>Golden Globe</award><count>1</count></record><record><id>tt4016934</id><award>BAFTA Film Award</award><count>1</count></record><record><id>tt1895587</id><award>BAFTA Film Award</award><count>1</count></record><record><id>tt1895587</id><award>Oscar</award><count>2</count></record><record><id>tt2562232</id><award>Golden Globe</award><count>2</count></record><record><id>tt2562232</id><award>BAFTA Film Award</award><count>1</count></record><record><id>tt2562232</id><award>Oscar</award><count>4</count></record><record><id>tt0096874</id><award>BAFTA Film Award</award><count>1</count></record><record><id>tt0790636</id><award>Golden Globe</award><count>2</count></record><record><id>tt0790636</id><award>Oscar</award><count>3</count></record><record><id>tt0317248</id><award>BAFTA Film Award</award><count>1</count></record><record><id>tt0758758</id><award>Golden Globe</award><count>1</count></record><record><id>tt0087843</id><award>BAFTA Film Award</award><count>2</count></record><record><id>tt0783233</id><award>Oscar</award><count>1</count></record><record><id>tt0783233</id><award>Golden Globe</award><count>2</count></record><record><id>tt0783233</id><award>BAFTA Film Award</award><count>2</count></record><record><id>tt0031381</id><award>Oscar</award><count>8</count></record><record><id>tt0075148</id><award>Oscar</award><count>3</count></record><record><id>tt0075148</id><award>Golden Globe</award><count>1</count></record><record><id>tt0106977</id><award>Oscar</award><count>1</count></record><record><id>tt0106977</id><award>Golden Globe</award><count>1</count></record><record><id>tt0106977</id><award>BAFTA Film Award</award><count>1</count></record><record><id>tt0054215</id><award>Golden Globe</award><count>1</count></record><record><id>tt0061512</id><award>Oscar</award><count>1</count></record><record><id>tt0087469</id><award>Oscar</award><count>1</count></record><record><id>tt0087469</id><award>BAFTA Film Award</award><count>1</count></record><record><id>tt2096673</id><award>Golden Globe</award><count>1</count></record><record><id>tt2096673</id><award>BAFTA Film Award</award><count>1</count></record><record><id>tt2096673</id><award>Oscar</award><count>1</count></record><record><id>tt0034583</id><award>Oscar</award><count>3</count></record><record><id>tt0073195</id><award>Oscar</award><count>3</count></record><record><id>tt0073195</id><award>Golden Globe</award><count>1</count></record><record><id>tt0317705</id><award>Oscar</award><count>2</count></record><record><id>tt0058150</id><award>Oscar</award><count>1</count></record><record><id>tt4034228</id><award>Golden Globe</award><count>1</count></record><record><id>tt4034228</id><award>BAFTA Film Award</award><count>2</count></record><record><id>tt4034228</id><award>Oscar</award><count>2</count></record><record><id>tt0112641</id><award>Golden Globe</award><count>1</count></record><record><id>tt1024648</id><award>Golden Globe</award><count>2</count></record><record><id>tt1024648</id><award>BAFTA Film Award</award><count>2</count></record><record><id>tt1024648</id><award>Oscar</award><count>3</count></record><record><id>tt0117951</id><award>BAFTA Film Award</award><count>1</count></record><record><id>tt0878804</id><award>Oscar</award><count>1</count></record><record><id>tt0878804</id><award>Golden Globe</award><count>1</count></record><record><id>tt0053604</id><award>Oscar</award><count>5</count></record><record><id>tt0053604</id><award>Golden Globe</award><count>3</count></record><record><id>tt0053604</id><award>BAFTA Film Award</award><count>3</count></record><record><id>tt0988045</id><award>Golden Globe</award><count>1</count></record><record><id>tt0162222</id><award>Golden Globe</award><count>1</count></record><record><id>tt0119488</id><award>Oscar</award><count>2</count></record><record><id>tt0119488</id><award>Golden Globe</award><count>1</count></record><record><id>tt0119488</id><award>BAFTA Film Award</award><count>2</count></record><record><id>tt0086197</id><award>Oscar</award><count>4</count></record><record><id>tt0265086</id><award>Oscar</award><count>2</count></record><record><id>tt0257044</id><award>Oscar</award><count>1</count></record><record><id>tt0257044</id><award>BAFTA Film Award</award><count>2</count></record><record><id>tt0036868</id><award>Oscar</award><count>7</count></record><record><id>tt0036868</id><award>Golden Globe</award><count>1</count></record><record><id>tt0036868</id><award>BAFTA Film Award</award><count>1</count></record><record><id>tt0058331</id><award>Oscar</award><count>5</count></record><record><id>tt0058331</id><award>Golden Globe</award><count>1</count></record><record><id>tt0058331</id><award>BAFTA Film Award</award><count>1</count></record><record><id>tt0266543</id><award>Oscar</award><count>1</count></record><record><id>tt0070047</id><award>Oscar</award><count>2</count></record><record><id>tt0070047</id><award>Golden Globe</award><count>4</count></record><record><id>tt0780536</id><award>Golden Globe</award><count>1</count></record><record><id>tt0780536</id><award>BAFTA Film Award</award><count>1</count></record><record><id>tt1010048</id><award>Oscar</award><count>8</count></record><record><id>tt1010048</id><award>Golden Globe</award><count>4</count></record><record><id>tt1010048</id><award>BAFTA Film Award</award><count>5</count></record><record><id>tt0086879</id><award>Oscar</award><count>8</count></record><record><id>tt0086879</id><award>Golden Globe</award><count>4</count></record><record><id>tt0086879</id><award>BAFTA Film Award</award><count>4</count></record><record><id>tt0075860</id><award>Oscar</award><count>1</count></record><record><id>tt0075860</id><award>BAFTA Film Award</award><count>1</count></record><record><id>tt2980516</id><award>Golden Globe</award><count>2</count></record><record><id>tt2980516</id><award>BAFTA Film Award</award><count>2</count></record><record><id>tt2980516</id><award>Oscar</award><count>1</count></record><record><id>tt1979320</id><award>BAFTA Film Award</award><count>1</count></record><record><id>tt0449059</id><award>Oscar</award><count>2</count></record><record><id>tt0449059</id><award>BAFTA Film Award</award><count>2</count></record><record><id>tt3741834</id><award>BAFTA Film Award</award><count>2</count></record><record><id>tt0327056</id><award>Oscar</award><count>2</count></record><record><id>tt0327056</id><award>Golden Globe</award><count>2</count></record><record><id>tt0910970</id><award>Oscar</award><count>1</count></record><record><id>tt0910970</id><award>BAFTA Film Award</award><count>1</count></record><record><id>tt0910970</id><award>Golden Globe</award><count>1</count></record><record><id>tt1049413</id><award>Oscar</award><count>2</count></record><record><id>tt1049413</id><award>Golden Globe</award><count>2</count></record><record><id>tt1049413</id><award>BAFTA Film Award</award><count>1</count></record><record><id>tt0057012</id><award>BAFTA Film Award</award><count>3</count></record><record><id>tt0198781</id><award>Oscar</award><count>1</count></record><record><id>tt0054698</id><award>Oscar</award><count>2</count></record><record><id>tt0249462</id><award>BAFTA Film Award</award><count>2</count></record><record><id>tt0104952</id><award>Oscar</award><count>1</count></record><record><id>tt0190590</id><award>Golden Globe</award><count>1</count></record><record><id>tt0405094</id><award>Oscar</award><count>1</count></record><record><id>tt0405094</id><award>BAFTA Film Award</award><count>1</count></record><record><id>tt0405094</id><award>Golden Globe</award><count>3</count></record><record><id>tt0119822</id><award>Oscar</award><count>2</count></record><record><id>tt0119822</id><award>Golden Globe</award><count>3</count></record><record><id>tt0435761</id><award>BAFTA Film Award</award><count>1</count></record><record><id>tt0435761</id><award>Oscar</award><count>2</count></record><record><id>tt0435761</id><award>Golden Globe</award><count>1</count></record><record><id>tt0139654</id><award>Oscar</award><count>1</count></record><record><id>tt0114746</id><award>Golden Globe</award><count>1</count></record><record><id>tt0175880</id><award>Golden Globe</award><count>1</count></record><record><id>tt3682448</id><award>BAFTA Film Award</award><count>1</count></record><record><id>tt3682448</id><award>Oscar</award><count>1</count></record><record><id>tt0063522</id><award>Oscar</award><count>1</count></record><record><id>tt0063522</id><award>Golden Globe</award><count>1</count></record><record><id>tt0117381</id><award>Golden Globe</award><count>1</count></record><record><id>tt0101414</id><award>Oscar</award><count>2</count></record><record><id>tt0101414</id><award>Golden Globe</award><count>3</count></record><record><id>tt0061722</id><award>Oscar</award><count>1</count></record><record><id>tt0061722</id><award>Golden Globe</award><count>5</count></record><record><id>tt0061722</id><award>BAFTA Film Award</award><count>5</count></record><record><id>tt0358273</id><award>Oscar</award><count>1</count></record><record><id>tt0358273</id><award>Golden Globe</award><count>3</count></record><record><id>tt0358273</id><award>BAFTA Film Award</award><count>2</count></record><record><id>tt0081398</id><award>Oscar</award><count>2</count></record><record><id>tt0081398</id><award>Golden Globe</award><count>1</count></record><record><id>tt0081398</id><award>BAFTA Film Award</award><count>2</count></record><record><id>tt0071315</id><award>Oscar</award><count>1</count></record><record><id>tt0071315</id><award>Golden Globe</award><count>4</count></record><record><id>tt0071315</id><award>BAFTA Film Award</award><count>3</count></record><record><id>tt1605783</id><award>Golden Globe</award><count>1</count></record><record><id>tt1605783</id><award>Oscar</award><count>1</count></record><record><id>tt0405159</id><award>Oscar</award><count>4</count></record><record><id>tt0405159</id><award>Golden Globe</award><count>2</count></record><record><id>tt0095953</id><award>Oscar</award><count>4</count></record><record><id>tt0095953</id><award>Golden Globe</award><count>2</count></record><record><id>tt0375679</id><award>Oscar</award><count>3</count></record><record><id>tt0375679</id><award>BAFTA Film Award</award><count>2</count></record><record><id>tt0120363</id><award>Golden Globe</award><count>1</count></record><record><id>tt0056172</id><award>Oscar</award><count>7</count></record><record><id>tt0056172</id><award>Golden Globe</award><count>6</count></record><record><id>tt0056172</id><award>BAFTA Film Award</award><count>4</count></record><record><id>tt0265666</id><award>Golden Globe</award><count>1</count></record><record><id>tt0964517</id><award>Golden Globe</award><count>2</count></record><record><id>tt0964517</id><award>Oscar</award><count>2</count></record><record><id>tt0088846</id><award>BAFTA Film Award</award><count>2</count></record><record><id>tt0080678</id><award>BAFTA Film Award</award><count>3</count></record><record><id>tt1454468</id><award>Golden Globe</award><count>1</count></record><record><id>tt1454468</id><award>BAFTA Film Award</award><count>3</count></record><record><id>tt1454468</id><award>Oscar</award><count>7</count></record><record><id>tt0120601</id><award>BAFTA Film Award</award><count>1</count></record><record><id>tt0114388</id><award>Oscar</award><count>1</count></record><record><id>tt0114388</id><award>Golden Globe</award><count>2</count></record><record><id>tt0114388</id><award>BAFTA Film Award</award><count>3</count></record><record><id>tt0097441</id><award>Oscar</award><count>3</count></record><record><id>tt0097441</id><award>Golden Globe</award><count>1</count></record><record><id>tt2245084</id><award>Oscar</award><count>1</count></record><record><id>tt0032976</id><award>Oscar</award><count>2</count></record><record><id>tt0181865</id><award>Oscar</award><count>4</count></record><record><id>tt0181865</id><award>Golden Globe</award><count>2</count></record><record><id>tt0181865</id><award>BAFTA Film Award</award><count>2</count></record><record><id>tt1132620</id><award>BAFTA Film Award</award><count>1</count></record><record><id>tt0103639</id><award>Oscar</award><count>2</count></record><record><id>tt0103639</id><award>Golden Globe</award><count>2</count></record><record><id>tt0092965</id><award>BAFTA Film Award</award><count>3</count></record><record><id>tt0067093</id><award>Oscar</award><count>3</count></record><record><id>tt0067093</id><award>Golden Globe</award><count>2</count></record><record><id>tt0190332</id><award>Oscar</award><count>4</count></record><record><id>tt0190332</id><award>Golden Globe</award><count>2</count></record><record><id>tt0190332</id><award>BAFTA Film Award</award><count>2</count></record><record><id>tt0097757</id><award>Oscar</award><count>2</count></record><record><id>tt0097757</id><award>Golden Globe</award><count>2</count></record><record><id>tt0091064</id><award>Oscar</award><count>1</count></record><record><id>tt1305806</id><award>Oscar</award><count>1</count></record><record><id>tt0095765</id><award>Oscar</award><count>1</count></record><record><id>tt0095765</id><award>Golden Globe</award><count>1</count></record><record><id>tt0095765</id><award>BAFTA Film Award</award><count>5</count></record><record><id>tt0454876</id><award>Golden Globe</award><count>1</count></record><record><id>tt0454876</id><award>BAFTA Film Award</award><count>2</count></record><record><id>tt0454876</id><award>Oscar</award><count>4</count></record><record><id>tt0102138</id><award>Oscar</award><count>2</count></record><record><id>tt0102138</id><award>Golden Globe</award><count>1</count></record><record><id>tt0102138</id><award>BAFTA Film Award</award><count>2</count></record><record><id>tt0440963</id><award>Oscar</award><count>3</count></record><record><id>tt0440963</id><award>BAFTA Film Award</award><count>2</count></record><record><id>tt0072684</id><award>Oscar</award><count>4</count></record><record><id>tt0072684</id><award>BAFTA Film Award</award><count>2</count></record><record><id>tt0098635</id><award>BAFTA Film Award</award><count>1</count></record><record><id>tt3076658</id><award>Golden Globe</award><count>1</count></record><record><id>tt0096438</id><award>Oscar</award><count>3</count></record><record><id>tt0096438</id><award>BAFTA Film Award</award><count>1</count></record><record><id>tt0064115</id><award>Oscar</award><count>4</count></record><record><id>tt0064115</id><award>Golden Globe</award><count>1</count></record><record><id>tt0064115</id><award>BAFTA Film Award</award><count>8</count></record><record><id>tt0045152</id><award>Golden Globe</award><count>1</count></record><record><id>tt6155172</id><award>Golden Globe</award><count>2</count></record><record><id>tt6155172</id><award>Oscar</award><count>3</count></record><record><id>tt6155172</id><award>BAFTA Film Award</award><count>3</count></record><record><id>tt0107818</id><award>Oscar</award><count>2</count></record><record><id>tt0107818</id><award>Golden Globe</award><count>2</count></record><record><id>tt0056592</id><award>Oscar</award><count>3</count></record><record><id>tt0056592</id><award>Golden Globe</award><count>3</count></record><record><id>tt0056869</id><award>Golden Globe</award><count>1</count></record><record><id>tt0052618</id><award>Oscar</award><count>11</count></record><record><id>tt0052618</id><award>Golden Globe</award><count>3</count></record><record><id>tt0052618</id><award>BAFTA Film Award</award><count>1</count></record><record><id>tt1182345</id><award>BAFTA Film Award</award><count>1</count></record><record><id>tt1125849</id><award>Golden Globe</award><count>2</count></record><record><id>tt1125849</id><award>BAFTA Film Award</award><count>1</count></record><record><id>tt0049833</id><award>Oscar</award><count>1</count></record><record><id>tt1490017</id><award>BAFTA Film Award</award><count>1</count></record><record><id>tt1535109</id><award>BAFTA Film Award</award><count>1</count></record><record><id>tt0268126</id><award>Oscar</award><count>1</count></record><record><id>tt0268126</id><award>Golden Globe</award><count>2</count></record><record><id>tt0268126</id><award>BAFTA Film Award</award><count>1</count></record><record><id>tt3011894</id><award>BAFTA Film Award</award><count>1</count></record><record><id>tt0088939</id><award>Golden Globe</award><count>1</count></record><record><id>tt0070735</id><award>Oscar</award><count>7</count></record><record><id>tt0054331</id><award>Oscar</award><count>4</count></record><record><id>tt0054331</id><award>Golden Globe</award><count>1</count></record><record><id>tt1065073</id><award>Golden Globe</award><count>3</count></record><record><id>tt1065073</id><award>BAFTA Film Award</award><count>2</count></record><record><id>tt1065073</id><award>Oscar</award><count>1</count></record><record><id>tt0091605</id><award>BAFTA Film Award</award><count>2</count></record><record><id>tt0059113</id><award>Oscar</award><count>5</count></record><record><id>tt0059113</id><award>Golden Globe</award><count>5</count></record><record><id>tt0075686</id><award>Oscar</award><count>4</count></record><record><id>tt0075686</id><award>Golden Globe</award><count>1</count></record><record><id>tt0075686</id><award>BAFTA Film Award</award><count>5</count></record><record><id>tt1189073</id><award>BAFTA Film Award</award><count>1</count></record><record><id>tt0043014</id><award>Oscar</award><count>3</count></record><record><id>tt0043014</id><award>Golden Globe</award><count>4</count></record><record><id>tt0087884</id><award>BAFTA Film Award</award><count>1</count></record><record><id>tt0053291</id><award>Oscar</award><count>1</count></record><record><id>tt0053291</id><award>Golden Globe</award><count>3</count></record><record><id>tt0053291</id><award>BAFTA Film Award</award><count>1</count></record><record><id>tt0245712</id><award>BAFTA Film Award</award><count>1</count></record><record><id>tt0064665</id><award>Oscar</award><count>3</count></record><record><id>tt0064665</id><award>Golden Globe</award><count>1</count></record><record><id>tt0064665</id><award>BAFTA Film Award</award><count>6</count></record><record><id>tt0350258</id><award>Oscar</award><count>2</count></record><record><id>tt0350258</id><award>Golden Globe</award><count>1</count></record><record><id>tt0350258</id><award>BAFTA Film Award</award><count>2</count></record><record><id>tt0455590</id><award>Oscar</award><count>1</count></record><record><id>tt0455590</id><award>Golden Globe</award><count>1</count></record><record><id>tt0455590</id><award>BAFTA Film Award</award><count>2</count></record><record><id>tt0046250</id><award>Oscar</award><count>3</count></record><record><id>tt0046250</id><award>Golden Globe</award><count>1</count></record><record><id>tt0046250</id><award>BAFTA Film Award</award><count>1</count></record><record><id>tt0058385</id><award>Oscar</award><count>8</count></record><record><id>tt0058385</id><award>Golden Globe</award><count>3</count></record><record><id>tt0058385</id><award>BAFTA Film Award</award><count>1</count></record><record><id>tt0093389</id><award>Oscar</award><count>9</count></record><record><id>tt0093389</id><award>Golden Globe</award><count>4</count></record><record><id>tt0093389</id><award>BAFTA Film Award</award><count>3</count></record><record><id>tt0067328</id><award>Oscar</award><count>2</count></record><record><id>tt0067328</id><award>Golden Globe</award><count>1</count></record><record><id>tt0067328</id><award>BAFTA Film Award</award><count>3</count></record><record><id>tt0450188</id><award>Oscar</award><count>2</count></record><record><id>tt0450188</id><award>Golden Globe</award><count>1</count></record><record><id>tt0450188</id><award>BAFTA Film Award</award><count>3</count></record><record><id>tt0071360</id><award>BAFTA Film Award</award><count>2</count></record><record><id>tt0072890</id><award>Oscar</award><count>1</count></record><record><id>tt0072890</id><award>BAFTA Film Award</award><count>2</count></record><record><id>tt0083922</id><award>Oscar</award><count>4</count></record><record><id>tt0083922</id><award>Golden Globe</award><count>1</count></record><record><id>tt0083922</id><award>BAFTA Film Award</award><count>1</count></record><record><id>tt0308644</id><award>Oscar</award><count>1</count></record><record><id>tt1655442</id><award>Golden Globe</award><count>3</count></record><record><id>tt1655442</id><award>BAFTA Film Award</award><count>5</count></record><record><id>tt1655442</id><award>Oscar</award><count>5</count></record><record><id>tt0049730</id><award>Golden Globe</award><count>1</count></record><record><id>tt0107943</id><award>BAFTA Film Award</award><count>1</count></record><record><id>tt1832382</id><award>Golden Globe</award><count>1</count></record><record><id>tt1832382</id><award>Oscar</award><count>1</count></record><record><id>tt0070666</id><award>Golden Globe</award><count>1</count></record><record><id>tt0095647</id><award>Oscar</award><count>1</count></record><record><id>tt0095647</id><award>BAFTA Film Award</award><count>3</count></record><record><id>tt0047296</id><award>Oscar</award><count>8</count></record><record><id>tt0047296</id><award>Golden Globe</award><count>4</count></record><record><id>tt0047296</id><award>BAFTA Film Award</award><count>1</count></record><record><id>tt0043456</id><award>Golden Globe</award><count>1</count></record><record><id>tt0056801</id><award>Oscar</award><count>2</count></record><record><id>tt0044081</id><award>Oscar</award><count>4</count></record><record><id>tt0044081</id><award>Golden Globe</award><count>1</count></record><record><id>tt0044081</id><award>BAFTA Film Award</award><count>1</count></record><record><id>tt0079417</id><award>Oscar</award><count>5</count></record><record><id>tt0079417</id><award>Golden Globe</award><count>4</count></record><record><id>tt0089881</id><award>Oscar</award><count>1</count></record><record><id>tt0089881</id><award>BAFTA Film Award</award><count>2</count></record><record><id>tt0077928</id><award>Oscar</award><count>2</count></record><record><id>tt0077928</id><award>Golden Globe</award><count>6</count></record><record><id>tt0077928</id><award>BAFTA Film Award</award><count>3</count></record><record><id>tt0047437</id><award>Oscar</award><count>1</count></record><record><id>tt0047437</id><award>Golden Globe</award><count>1</count></record><record><id>tt0117666</id><award>Oscar</award><count>1</count></record><record><id>tt0041959</id><award>Oscar</award><count>1</count></record><record><id>tt0041959</id><award>BAFTA Film Award</award><count>1</count></record><record><id>tt0056923</id><award>BAFTA Film Award</award><count>1</count></record><record><id>tt0061418</id><award>Oscar</award><count>2</count></record><record><id>tt0061418</id><award>BAFTA Film Award</award><count>1</count></record><record><id>tt0050212</id><award>Oscar</award><count>7</count></record><record><id>tt0050212</id><award>Golden Globe</award><count>3</count></record><record><id>tt0050212</id><award>BAFTA Film Award</award><count>4</count></record><record><id>tt0083987</id><award>Oscar</award><count>8</count></record><record><id>tt0083987</id><award>Golden Globe</award><count>5</count></record><record><id>tt0083987</id><award>BAFTA Film Award</award><count>5</count></record><record><id>tt0097937</id><award>Oscar</award><count>2</count></record><record><id>tt0097937</id><award>BAFTA Film Award</award><count>2</count></record><record><id>tt0032904</id><award>Oscar</award><count>2</count></record><record><id>tt0077405</id><award>Oscar</award><count>1</count></record><record><id>tt0049261</id><award>Oscar</award><count>1</count></record><record><id>tt0049261</id><award>Golden Globe</award><count>1</count></record><record><id>tt0109707</id><award>Oscar</award><count>2</count></record><record><id>tt0109707</id><award>Golden Globe</award><count>1</count></record><record><id>tt0074958</id><award>Oscar</award><count>4</count></record><record><id>tt0074958</id><award>Golden Globe</award><count>4</count></record><record><id>tt0074958</id><award>BAFTA Film Award</award><count>1</count></record><record><id>tt3169706</id><award>BAFTA Film Award</award><count>1</count></record><record><id>tt0081283</id><award>Oscar</award><count>4</count></record><record><id>tt0081283</id><award>Golden Globe</award><count>5</count></record><record><id>tt2358891</id><award>Golden Globe</award><count>2</count></record><record><id>tt2358891</id><award>BAFTA Film Award</award><count>1</count></record><record><id>tt2358891</id><award>Oscar</award><count>1</count></record><record><id>tt0087553</id><award>Oscar</award><count>3</count></record><record><id>tt0087553</id><award>Golden Globe</award><count>1</count></record><record><id>tt0087553</id><award>BAFTA Film Award</award><count>8</count></record><record><id>tt0085794</id><award>BAFTA Film Award</award><count>1</count></record><record><id>tt0048545</id><award>Golden Globe</award><count>1</count></record><record><id>tt0067116</id><award>Oscar</award><count>5</count></record><record><id>tt0067116</id><award>Golden Globe</award><count>3</count></record><record><id>tt0067116</id><award>BAFTA Film Award</award><count>2</count></record><record><id>tt0068327</id><award>Oscar</award><count>8</count></record><record><id>tt0068327</id><award>Golden Globe</award><count>3</count></record><record><id>tt0068327</id><award>BAFTA Film Award</award><count>7</count></record><record><id>tt0042192</id><award>Oscar</award><count>6</count></record><record><id>tt0042192</id><award>Golden Globe</award><count>1</count></record><record><id>tt0042192</id><award>BAFTA Film Award</award><count>1</count></record><record><id>tt1646971</id><award>Golden Globe</award><count>1</count></record><record><id>tt0061578</id><award>Oscar</award><count>1</count></record><record><id>tt0045793</id><award>Oscar</award><count>8</count></record><record><id>tt0045793</id><award>Golden Globe</award><count>2</count></record><record><id>tt0045061</id><award>Oscar</award><count>2</count></record><record><id>tt0074119</id><award>Oscar</award><count>4</count></record><record><id>tt0063227</id><award>Oscar</award><count>3</count></record><record><id>tt0063227</id><award>Golden Globe</award><count>2</count></record><record><id>tt0063227</id><award>BAFTA Film Award</award><count>1</count></record><record><id>tt0040522</id><award>Golden Globe</award><count>1</count></record><record><id>tt0040522</id><award>BAFTA Film Award</award><count>1</count></record><record><id>tt0051201</id><award>Golden Globe</award><count>1</count></record><record><id>tt0056197</id><award>Oscar</award><count>2</count></record><record><id>tt0056197</id><award>Golden Globe</award><count>1</count></record><record><id>tt0044706</id><award>Oscar</award><count>4</count></record><record><id>tt0044706</id><award>Golden Globe</award><count>4</count></record><record><id>tt0078841</id><award>Oscar</award><count>1</count></record><record><id>tt0078841</id><award>Golden Globe</award><count>2</count></record><record><id>tt0078841</id><award>BAFTA Film Award</award><count>1</count></record><record><id>tt0498380</id><award>Oscar</award><count>1</count></record><record><id>tt0498380</id><award>Golden Globe</award><count>1</count></record><record><id>tt0054997</id><award>Oscar</award><count>2</count></record><record><id>tt0054997</id><award>BAFTA Film Award</award><count>2</count></record><record><id>tt0117589</id><award>Golden Globe</award><count>1</count></record><record><id>tt0117589</id><award>BAFTA Film Award</award><count>2</count></record><record><id>tt0053779</id><award>Oscar</award><count>1</count></record><record><id>tt4302938</id><award>BAFTA Film Award</award><count>1</count></record><record><id>tt0055031</id><award>Oscar</award><count>2</count></record><record><id>tt0055031</id><award>Golden Globe</award><count>2</count></record><record><id>tt0040897</id><award>Oscar</award><count>3</count></record><record><id>tt0040897</id><award>Golden Globe</award><count>3</count></record><record><id>tt0025316</id><award>Oscar</award><count>5</count></record><record><id>tt0046268</id><award>BAFTA Film Award</award><count>1</count></record><record><id>tt0066206</id><award>Oscar</award><count>7</count></record><record><id>tt0066206</id><award>Golden Globe</award><count>1</count></record><record><id>tt0079522</id><award>BAFTA Film Award</award><count>2</count></record><record><id>tt0077711</id><award>Golden Globe</award><count>1</count></record><record><id>tt0907657</id><award>Oscar</award><count>1</count></record><record><id>tt0061811</id><award>Oscar</award><count>5</count></record><record><id>tt0061811</id><award>Golden Globe</award><count>3</count></record><record><id>tt0061811</id><award>BAFTA Film Award</award><count>1</count></record><record><id>tt0031679</id><award>Oscar</award><count>1</count></record><record><id>tt1602620</id><award>Golden Globe</award><count>1</count></record><record><id>tt1602620</id><award>BAFTA Film Award</award><count>2</count></record><record><id>tt1602620</id><award>Oscar</award><count>1</count></record><record><id>tt0053221</id><award>Golden Globe</award><count>1</count></record><record><id>tt0061735</id><award>Oscar</award><count>2</count></record><record><id>tt0061735</id><award>BAFTA Film Award</award><count>2</count></record><record><id>tt0056218</id><award>Golden Globe</award><count>1</count></record><record><id>tt0084503</id><award>BAFTA Film Award</award><count>2</count></record><record><id>tt0070510</id><award>Oscar</award><count>1</count></record><record><id>tt0070510</id><award>Golden Globe</award><count>1</count></record><record><id>tt0091167</id><award>Oscar</award><count>3</count></record><record><id>tt0091167</id><award>BAFTA Film Award</award><count>2</count></record><record><id>tt0091167</id><award>Golden Globe</award><count>1</count></record><record><id>tt0050986</id><award>Golden Globe</award><count>1</count></record><record><id>tt5168192</id><award>BAFTA Film Award</award><count>1</count></record><record><id>tt0120731</id><award>Golden Globe</award><count>2</count></record><record><id>tt0056687</id><award>Oscar</award><count>1</count></record><record><id>tt0048028</id><award>Oscar</award><count>1</count></record><record><id>tt0048028</id><award>Golden Globe</award><count>1</count></record><record><id>tt0046359</id><award>Oscar</award><count>1</count></record><record><id>tt0040725</id><award>Oscar</award><count>2</count></record><record><id>tt0040725</id><award>Golden Globe</award><count>1</count></record><record><id>tt0029843</id><award>Oscar</award><count>3</count></record><record><id>tt0174856</id><award>Golden Globe</award><count>1</count></record><record><id>tt0082846</id><award>Oscar</award><count>3</count></record><record><id>tt0082846</id><award>Golden Globe</award><count>3</count></record><record><id>tt0082846</id><award>BAFTA Film Award</award><count>1</count></record><record><id>tt1235166</id><award>BAFTA Film Award</award><count>1</count></record><record><id>tt0043265</id><award>Oscar</award><count>1</count></record><record><id>tt0185125</id><award>Golden Globe</award><count>1</count></record><record><id>tt0185125</id><award>BAFTA Film Award</award><count>1</count></record><record><id>tt0185125</id><award>Oscar</award><count>1</count></record><record><id>tt0069947</id><award>BAFTA Film Award</award><count>1</count></record><record><id>tt0032551</id><award>Oscar</award><count>2</count></record><record><id>tt0401383</id><award>Golden Globe</award><count>2</count></record><record><id>tt0401383</id><award>BAFTA Film Award</award><count>1</count></record><record><id>tt0287467</id><award>Oscar</award><count>1</count></record><record><id>tt0287467</id><award>Golden Globe</award><count>1</count></record><record><id>tt0287467</id><award>BAFTA Film Award</award><count>2</count></record><record><id>tt0042546</id><award>Oscar</award><count>1</count></record><record><id>tt0042546</id><award>Golden Globe</award><count>1</count></record><record><id>tt0117631</id><award>Oscar</award><count>1</count></record><record><id>tt0117631</id><award>Golden Globe</award><count>1</count></record><record><id>tt0117631</id><award>BAFTA Film Award</award><count>2</count></record><record><id>tt5186714</id><award>Oscar</award><count>1</count></record><record><id>tt1149362</id><award>Golden Globe</award><count>1</count></record><record><id>tt0369702</id><award>Oscar</award><count>1</count></record><record><id>tt0369702</id><award>Golden Globe</award><count>1</count></record><record><id>tt0031971</id><award>Oscar</award><count>2</count></record><record><id>tt0071129</id><award>Oscar</award><count>1</count></record><record><id>tt0071129</id><award>Golden Globe</award><count>1</count></record><record><id>tt0020629</id><award>Oscar</award><count>2</count></record><record><id>tt0061184</id><award>Oscar</award><count>5</count></record><record><id>tt0061184</id><award>BAFTA Film Award</award><count>3</count></record><record><id>tt2802154</id><award>Golden Globe</award><count>1</count></record><record><id>tt0080979</id><award>BAFTA Film Award</award><count>2</count></record><record><id>tt0069467</id><award>Oscar</award><count>1</count></record><record><id>tt0318462</id><award>Oscar</award><count>1</count></record><record><id>tt0318462</id><award>BAFTA Film Award</award><count>1</count></record><record><id>tt0037008</id><award>Oscar</award><count>1</count></record><record><id>tt0101640</id><award>BAFTA Film Award</award><count>1</count></record><record><id>tt0047528</id><award>Oscar</award><count>1</count></record><record><id>tt2431286</id><award>BAFTA Film Award</award><count>1</count></record><record><id>tt0283509</id><award>Golden Globe</award><count>1</count></record><record><id>tt0283509</id><award>Oscar</award><count>1</count></record><record><id>tt1340107</id><award>Golden Globe</award><count>3</count></record><record><id>tt1340107</id><award>Oscar</award><count>1</count></record><record><id>tt0060665</id><award>Oscar</award><count>6</count></record><record><id>tt0060665</id><award>Golden Globe</award><count>4</count></record><record><id>tt0060665</id><award>BAFTA Film Award</award><count>7</count></record><record><id>tt0340377</id><award>BAFTA Film Award</award><count>1</count></record><record><id>tt0018455</id><award>Oscar</award><count>3</count></record><record><id>tt0092593</id><award>BAFTA Film Award</award><count>1</count></record><record><id>tt0040506</id><award>Oscar</award><count>1</count></record><record><id>tt0048281</id><award>BAFTA Film Award</award><count>2</count></record><record><id>tt0140888</id><award>Golden Globe</award><count>1</count></record><record><id>tt0140888</id><award>BAFTA Film Award</award><count>1</count></record><record><id>tt0110877</id><award>Oscar</award><count>1</count></record><record><id>tt0110877</id><award>BAFTA Film Award</award><count>1</count></record><record><id>tt0110877</id><award>Golden Globe</award><count>2</count></record><record><id>tt0050783</id><award>Oscar</award><count>1</count></record><record><id>tt0068361</id><award>Oscar</award><count>1</count></record><record><id>tt0068361</id><award>BAFTA Film Award</award><count>2</count></record><record><id>tt0053976</id><award>Oscar</award><count>1</count></record><record><id>tt0053976</id><award>Golden Globe</award><count>1</count></record><record><id>tt0037884</id><award>Oscar</award><count>4</count></record><record><id>tt0037884</id><award>Golden Globe</award><count>3</count></record><record><id>tt1069238</id><award>Oscar</award><count>1</count></record><record><id>tt0089853</id><award>Golden Globe</award><count>1</count></record><record><id>tt0089853</id><award>BAFTA Film Award</award><count>2</count></record></awards>